baidu_image_crawling/__init__.py
baidu_image_crawling/main.py
baidu_image_crawling-0.0.1.dist-info/LICENSE
baidu_image_crawling-0.0.1.dist-info/METADATA
baidu_image_crawling-0.0.1.dist-info/WHEEL
baidu_image_crawling-0.0.1.dist-info/entry_points.txt
baidu_image_crawling-0.0.1.dist-info/top_level.txt
baidu_image_crawling-0.0.1.dist-info/RECORD
