Metadata-Version: 2.1
Name: baidu-image-crawling
Version: 0.0.1
Summary: Baidu Image Spider
Home-page: https://github.com/SWHL/BaiduImageCrawling
Author: SWHL
Author-email: liekkaskono@163.com
License: Apache-2.0
Keywords: spider,baidu
Platform: Any
Classifier: Programming Language :: Python :: 3.6
Classifier: Programming Language :: Python :: 3.7
Classifier: Programming Language :: Python :: 3.8
Classifier: Programming Language :: Python :: 3.9
Classifier: Programming Language :: Python :: 3.10
Classifier: Programming Language :: Python :: 3.11
Classifier: Programming Language :: Python :: 3.12
Requires-Python: >=3.6,<3.13
License-File: LICENSE
Requires-Dist: fake-useragent
